augmenter/__init__.py
augmenter/augmenter.py
augmenter-0.1.0.dist-info/METADATA
augmenter-0.1.0.dist-info/WHEEL
augmenter-0.1.0.dist-info/top_level.txt
augmenter-0.1.0.dist-info/RECORD
