Metadata-Version: 2.1
Name: augmenter
Version: 0.1.0
Summary: A toolkit for automated data augmentation
Home-page: https://github.com/IMApurbo/augmenter
Author: AKM Korishee Apurbo
Author-email: bandinvisible8@gmail.com
Classifier: Programming Language :: Python :: 3
Classifier: License :: OSI Approved :: MIT License
Classifier: Operating System :: OS Independent
Requires-Python: >=3.6
Requires-Dist: opencv-python
Requires-Dist: albumentations
